gpvisc/__init__.py
gpvisc/models.py
gpvisc/query.py
gpvisc/redox.py
gpvisc/utils.py
gpvisc/data/all_viscosity.hdf5
gpvisc/data/dataset+sciglass_lp.csv
gpvisc/data/dataset_hp.csv
gpvisc/models/GP_model1/X_train_valid.pth
gpvisc/models/GP_model1/Y_train_valid.pth
gpvisc/models/GP_model1/gp.pth
gpvisc/models/GP_model1/gp_loss.pdf
gpvisc/models/GP_model1/likelihood.pth
gpvisc/models/GP_model1/mean.pth
gpvisc/models/GP_model1/mean_f_loss.pdf
gpvisc/models/GP_model1/metrics.csv
gpvisc/models/GP_model2/X_train_valid.pth
gpvisc/models/GP_model2/Y_train_valid.pth
gpvisc/models/GP_model2/gp.pth
gpvisc/models/GP_model2/gp_loss.pdf
gpvisc/models/GP_model2/likelihood.pth
gpvisc/models/GP_model2/mean.pth
gpvisc/models/GP_model2/mean_f_loss.pdf
gpvisc/models/GP_model2/metrics.csv
gpvisc/models/GP_model3/X_train_valid.pth
gpvisc/models/GP_model3/Y_train_valid.pth
gpvisc/models/GP_model3/gp.pth
gpvisc/models/GP_model3/gp_loss.pdf
gpvisc/models/GP_model3/likelihood.pth
gpvisc/models/GP_model3/mean.pth
gpvisc/models/GP_model3/mean_f_loss.pdf
gpvisc/models/GP_model3/metrics.csv
gpvisc-0.3.5.dist-info/licenses/LICENSE.txt
gpvisc-0.3.5.dist-info/METADATA
gpvisc-0.3.5.dist-info/WHEEL
gpvisc-0.3.5.dist-info/top_level.txt
gpvisc-0.3.5.dist-info/RECORD
