Metadata-Version: 2.4
Name: gpvisc
Version: 0.3.5
Summary: A Python module containing a Gaussian Process - Artificial Neural Network model of melt viscosity
Author-email: Charles Le Losq <lelosq@ipgp.fr>, Clément Ferraina <ferraina@ipgp.fr>
Keywords: viscosity,liquid,glass,magma,phosphate,aluminosilicate
Classifier: Development Status :: 5 - Production/Stable
Classifier: Programming Language :: Python
Requires-Python: >=3.8
License-File: LICENSE.txt
Requires-Dist: numpy>=1.12
Requires-Dist: scipy
Requires-Dist: scikit-learn
Requires-Dist: pandas
Requires-Dist: xlrd
Requires-Dist: matplotlib
Requires-Dist: torch
Requires-Dist: gpytorch
Requires-Dist: h5py
Dynamic: license-file
